fat/__init__.py
fat-0.0.1.dist-info/LICENSE
fat-0.0.1.dist-info/METADATA
fat-0.0.1.dist-info/WHEEL
fat-0.0.1.dist-info/top_level.txt
fat-0.0.1.dist-info/RECORD
